[
  {
    "question": "What happens in the first 10 seconds of the video?",
    "answer": "A person walks into frame and sits down at a desk.",
    "reason": "Visual analysis of the first 10 seconds shows a clear entrance and seating action.",
    "timestamp": 1685432112.123
  },
  {
    "question": "How many people appear in the video?",
    "answer": "Three people appear in the video.",
    "reason": "Object detection identified three distinct human figures throughout the video.",
    "timestamp": 1685432342.543
  },
  {
    "question": "What is the main topic of discussion?",
    "answer": "The main topic is climate change solutions.",
    "reason": "Audio transcription analysis shows that 'climate change' and 'solutions' appear frequently and in key contexts.",
    "timestamp": 1685432487.876
  }
] 